{
 "id": "5a70d0ad21d33e9df627f666",
 "closed": true,
 "idList": "5858412042dabceed89d7d83",
 "idShort": 550,
 "idChecklists": [],
 "labels": [
  {
   "id": "57f2d33384e677fd36abfaf9",
   "idBoard": "57f2d333b99965a6ba8cd7e0",
   "name": "P3 - Will be fixed eventually",
   "color": "green"
  },
  {
   "id": "59ea289ff1ea9fc4b1173f7e",
   "idBoard": "57f2d333b99965a6ba8cd7e0",
   "name": "low",
   "color": "sky"
  }
 ],
 "shortUrl": "https://trello.com/c/EUI3ZeHo",
 "data": {
  "system_settings": "iPhone 8 + , iOS 11.3 Beta 1",
  "client_settings": "Discord TestFlight 2.2.2 (2352)",
  "actual_result": "Checkmark is missing.",
  "expected_result": "Checkmark is next to each status, like online, etc.",
  "short_description": "Checkmark missing from Status from your account.",
  "steps_to_repro": "- Click on your icon with status circle. - Observe."
 }
}