{
 "id": "5ae9aecaf3d698615020e3a3",
 "closed": true,
 "idList": "57fe7f78ddde6b37323bd670",
 "idShort": 1354,
 "idChecklists": [],
 "labels": [
  {
   "id": "57f2a30684e677fd36ab30e4",
   "idBoard": "57f2a306ca14741151990900",
   "name": "P3 - Will be fixed eventually",
   "color": "green"
  },
  {
   "id": "59d7e3881aa56dbcc6da1d7b",
   "idBoard": "57f2a306ca14741151990900",
   "name": "low",
   "color": "sky"
  }
 ],
 "shortUrl": "https://trello.com/c/QIMDAY9h",
 "data": {
  "system_settings": "Huawei Mate 9 Android 8.0",
  "client_settings": "Discord Alpha 6.6.0",
  "actual_result": "It shows as `https:// www. google. fr`, without the ending ?",
  "expected_result": "The message should show as `https:// www. google. fr?`",
  "short_description": "Links ending with ? won't show the ?",
  "steps_to_repro": "- Type/Paste a link ending with ? (nothing after). Example: `https:// www. google. fr?` - Send the message"
 }
}