{
 "id": "5bccb502702e510ed3e9b4d6",
 "closed": true,
 "idList": "57fe7f78ddde6b37323bd670",
 "idShort": 2213,
 "idChecklists": [],
 "labels": [
  {
   "id": "57f2a30684e677fd36ab30e4",
   "idBoard": "57f2a306ca14741151990900",
   "name": "P3 - Will be fixed eventually",
   "color": "green"
  },
  {
   "id": "59d7e3881aa56dbcc6da1d7b",
   "idBoard": "57f2a306ca14741151990900",
   "name": "low",
   "color": "sky"
  }
 ],
 "shortUrl": "https://trello.com/c/RFNJhZHt",
 "data": {
  "system_settings": "Lenovo vibe K5+, 5.1.1",
  "client_settings": "Discord Alpha 778",
  "actual_result": "You're taken to a point which is around 35~40 messages away from the blocked message.",
  "expected_result": "You're taken to the spot where the message is or at least near to it.",
  "short_description": "When you search messages from a blocked user and click on it, you are taken to a random spot (not quite) near the blocked message.",
  "steps_to_repro": "- Block a user. - Search a message by them. - Click on the message."
 }
}