{
 "id": "5b5d959a0546b45d1eeaf7c7",
 "closed": true,
 "idList": "57fe7f78ddde6b37323bd670",
 "idShort": 1709,
 "idChecklists": [],
 "labels": [
  {
   "id": "57f2a30684e677fd36ab30e4",
   "idBoard": "57f2a306ca14741151990900",
   "name": "P3 - Will be fixed eventually",
   "color": "green"
  },
  {
   "id": "59d7e3881aa56dbcc6da1d7b",
   "idBoard": "57f2a306ca14741151990900",
   "name": "low",
   "color": "sky"
  }
 ],
 "shortUrl": "https://trello.com/c/SEJfrqBC",
 "data": {
  "system_settings": "Honor 9, Android 8.0.0",
  "client_settings": "Discord Alpha 7.2.0",
  "actual_result": "You can't highlight the message.",
  "expected_result": "You should be able to highlight it.",
  "short_description": "Highlighted messages from a link will not highlight anymore.",
  "steps_to_repro": "- Click on a link to a message. - You'll see the message gets highlighted; now clicking on it will not highlight it anymore."
 }
}